ibw/__init__.py
ibw/client.py
ibw/client_certificates.py
ibw/clientportal.py
interactive_broker_python_web_api-0.1.2.dist-info/LICENSE
interactive_broker_python_web_api-0.1.2.dist-info/METADATA
interactive_broker_python_web_api-0.1.2.dist-info/WHEEL
interactive_broker_python_web_api-0.1.2.dist-info/top_level.txt
interactive_broker_python_web_api-0.1.2.dist-info/RECORD
